osmsg/__init__.py
osmsg/__version__.py
osmsg/app.py
osmsg/changefiles.py
osmsg/changesets.py
osmsg/login.py
osmsg/utils.py
osmsg-0.3.0.dist-info/entry_points.txt
osmsg-0.3.0.dist-info/WHEEL
osmsg-0.3.0.dist-info/METADATA
osmsg-0.3.0.dist-info/licenses/LICENSE
osmsg-0.3.0.dist-info/RECORD
