Metadata-Version: 2.1
Name: osmsg
Version: 0.3.0
Summary: OpenStreetMap Stats Generator: Commandline
License: GPL-3.0-only
Keywords: osm,stats,commandline,openstreetmap
Author-email: Kshitij Raj Sharma <skshitizraj@gmail.com>
Requires-Python: >=3.9
Classifier: Programming Language :: Python :: 3
Classifier: Programming Language :: Python :: 3.10
Classifier: Programming Language :: Python :: 3.11
Classifier: Programming Language :: Python :: 3.9
Classifier: Topic :: Scientific/Engineering :: GIS
Classifier: Topic :: Utilities
Requires-Dist: geopandas<=1.0.1
Requires-Dist: humanize<=4.10.0
Requires-Dist: matplotlib<=3.9.2
Requires-Dist: osmium<=3.7.0
Requires-Dist: pandas<=2.2.2
Requires-Dist: requests<=2.32.3
Requires-Dist: seaborn<=0.13.2
Requires-Dist: shapely<=2.0.6
Requires-Dist: tqdm<=4.66.5
Provides-Extra: docs
Requires-Dist: mkdocs>=1.5.3; extra == "docs"
Requires-Dist: mkdocs-material>=9.4.2; extra == "docs"
Requires-Dist: mkdocstrings-python>=1.7.0; extra == "docs"
Requires-Dist: mkdocs-exclude>=1.0.2; extra == "docs"
Provides-Extra: test
Requires-Dist: pytest>=7.4.2; extra == "test"
Requires-Dist: pytest-mock>=3.14.0; extra == "test"
Requires-Dist: coverage>=7.6.1; extra == "test"
Requires-Dist: coverage-badge>=1.1.2; extra == "test"
Project-URL: documentation, https://github.com/kshitijrajsharma/osmsg
Project-URL: homepage, https://github.com/kshitijrajsharma/osmsg
Project-URL: repository, https://github.com/kshitijrajsharma/osmsg
